utsc/switchconfig/__init__.py
utsc/switchconfig/__main__.py
utsc/switchconfig/deploy.py
utsc/switchconfig/example_template_dir/__init__.py
utsc/switchconfig/example_template_dir/comment-block-schema-example.j2
utsc/switchconfig/example_template_dir/data-model-example.j2
utsc/switchconfig/generate.py
utsc/switchconfig/types.py
utsc/switchconfig/util.py
utsc.switchconfig-2022.4.26.1.dist-info/entry_points.txt
utsc.switchconfig-2022.4.26.1.dist-info/WHEEL
utsc.switchconfig-2022.4.26.1.dist-info/METADATA
utsc.switchconfig-2022.4.26.1.dist-info/RECORD
